setup.py
bmi_calculate/__init__.py
bmi_calculate/bmi_calculate.py
bmi_calculate.egg-info/PKG-INFO
bmi_calculate.egg-info/SOURCES.txt
bmi_calculate.egg-info/dependency_links.txt
bmi_calculate.egg-info/not-zip-safe
bmi_calculate.egg-info/top_level.txt