Metadata-Version: 1.0
Name: bmi-calculate
Version: 0.1
Summary: Calculate Body-Mass Index
Home-page: UNKNOWN
Author: Vytautas Bielinskas
Author-email: UNKNOWN
License: UNKNOWN
Platform: UNKNOWN
